yamlfmt/__init__.py
yamlfmt/__main__.py
yamlfmt/_version.py
yamlfmt/_version.pyi
yamlfmt/yamlfmt
google_yamlfmt-0.21.0.dist-info/METADATA
google_yamlfmt-0.21.0.dist-info/WHEEL
google_yamlfmt-0.21.0.dist-info/entry_points.txt
google_yamlfmt-0.21.0.dist-info/licenses/LICENSE
google_yamlfmt-0.21.0.dist-info/RECORD
