Metadata-Version: 2.4
Name: google-yamlfmt
Version: 0.21.0
Summary: A tool for formatting YAML files, yamlfmt from Google: https://github.com/google/yamlfmt
Project-URL: Homepage, https://github.com/PFCCLab/google-yamlfmt
Project-URL: Repository, https://github.com/PFCCLab/google-yamlfmt
Project-URL: Issues, https://github.com/PFCCLab/google-yamlfmt/issues
License: MIT
License-File: LICENSE
Requires-Python: >=3.9
